rshf/__init__.py
rshf/utils.py
rshf/bioclip/__init__.py
rshf/bioclip/model.py
rshf/climplicit/__init__.py
rshf/climplicit/direct.py
rshf/climplicit/model.py
rshf/climplicit/siren.py
rshf/clip/__init__.py
rshf/croma/__init__.py
rshf/croma/model.py
rshf/geoclap/__init__.py
rshf/geoclip/__init__.py
rshf/geoclip/model.py
rshf/presto/__init__.py
rshf/presto/model.py
rshf/prithvi/__init__.py
rshf/prithvi/model.py
rshf/rcme/__init__.py
rshf/rcme/model.py
rshf/remoteclip/__init__.py
rshf/remoteclip/model.py
rshf/rvsa/__init__.py
rshf/rvsa/model.py
rshf/sat2cap/__init__.py
rshf/satclip/__init__.py
rshf/satclip/model.py
rshf/satclip/spherical_harmonics.py
rshf/satclip/spherical_harmonics_closed_form.py
rshf/satclip/spherical_harmonics_ylm.py
rshf/satmae/__init__.py
rshf/satmae/model.py
rshf/satmaepp/__init__.py
rshf/satmaepp/model.py
rshf/scalemae/__init__.py
rshf/scalemae/model.py
rshf/senclip/__init__.py
rshf/senclip/model.py
rshf/sinr/__init__.py
rshf/sinr/model.py
rshf/streetclip/__init__.py
rshf/taxabind/__init__.py
rshf/taxabind/model.py
rshf-0.1.11.dist-info/licenses/LICENSE
rshf-0.1.11.dist-info/METADATA
rshf-0.1.11.dist-info/WHEEL
rshf-0.1.11.dist-info/top_level.txt
rshf-0.1.11.dist-info/RECORD
