Metadata-Version: 2.4
Name: rshf
Version: 0.1.11
Summary: RS pretrained models in huggingface style
Home-page: https://github.com/mvrl/rshf
Author: Srikumar Sastry
Author-email: s.sastry@wustl.edu
Keywords: Remote Sensing,Huggingface
Classifier: Programming Language :: Python :: 3
Classifier: License :: OSI Approved :: Apache Software License
Classifier: Operating System :: OS Independent
Requires-Python: >=3.9
License-File: LICENSE
Requires-Dist: torch>=2.3.0
Requires-Dist: timm>=1.0.3
Requires-Dist: numpy>=2.0
Requires-Dist: huggingface_hub>=0.23.1
Requires-Dist: einops>=0.8.0
Requires-Dist: transformers>=4.41.1
Requires-Dist: open_clip_torch>=2.24.0
Requires-Dist: torchaudio
Requires-Dist: openai-clip>=1.0.1
Dynamic: license-file
